onionrblocks/__init__.py
onionrblocks/block.py
onionrblocks/customtypes.py
onionrblocks/universalrules.py
onionrblocks/blockcreator/__init__.py
onionrblocks/generators/__init__.py
onionrblocks/generators/anonvdf.py
onionrblocks-7.0.0.dist-info/LICENSE
onionrblocks-7.0.0.dist-info/METADATA
onionrblocks-7.0.0.dist-info/WHEEL
onionrblocks-7.0.0.dist-info/top_level.txt
onionrblocks-7.0.0.dist-info/RECORD
