Metadata-Version: 2.1
Name: onionrblocks
Version: 7.0.0
Summary: Onionr message format
Home-page: https://onionr.net/
Author: Kevin Froman
Author-email: beardog@mailbox.org
License: UNKNOWN
Platform: UNKNOWN
Classifier: Programming Language :: Python :: 3
Classifier: License :: OSI Approved :: GNU General Public License v3 (GPLv3)
Classifier: Operating System :: OS Independent
License-File: LICENSE
Requires-Dist: kasten (>=3.0.0)
Requires-Dist: pynacl (>=1.4.0)
